homesolar/__init__.py
homesolar/homesolar.py
homesolar/interfaces/__init__.py
homesolar/interfaces/database.py
homesolar/interfaces/mqtt.py
homesolar/services/__init__.py
homesolar/services/bluetooth.py
homesolar/services/control.py
homesolar/services/influxdb.py
homesolar/services/mqtt.py
homesolar/services/relayer.py
homesolar/services/sqlite.py
homesolar/utils/__init__.py
homesolar/utils/bluetooth.py
homesolar/utils/config.py
homesolar/utils/data_formatter.py
homesolar/utils/datetime.py
homesolar/utils/influxdb.py
homesolar/utils/mqtt.py
homesolar/utils/multiprocessing.py
homesolar/utils/sqlite.py
homesolar-0.7.20.dist-info/LICENSE
homesolar-0.7.20.dist-info/METADATA
homesolar-0.7.20.dist-info/WHEEL
homesolar-0.7.20.dist-info/top_level.txt
homesolar-0.7.20.dist-info/RECORD
